imqtt.py
imqtt-0.1.data/scripts/imqtt
imqtt-0.1.dist-info/DESCRIPTION.rst
imqtt-0.1.dist-info/METADATA
imqtt-0.1.dist-info/RECORD
imqtt-0.1.dist-info/WHEEL
imqtt-0.1.dist-info/metadata.json
imqtt-0.1.dist-info/top_level.txt
